bioclip/__about__.py
bioclip/__init__.py
bioclip/__main__.py
bioclip/predict.py
bioclip/recorder.py
pybioclip-2.1.1.dist-info/METADATA
pybioclip-2.1.1.dist-info/WHEEL
pybioclip-2.1.1.dist-info/entry_points.txt
pybioclip-2.1.1.dist-info/licenses/LICENSE
pybioclip-2.1.1.dist-info/RECORD
