Metadata-Version: 2.4
Name: pybioclip
Version: 2.1.1
Summary: Python package that simplifies using the BioCLIP foundation model.
Project-URL: Documentation, https://imageomics.github.io/pybioclip/
Project-URL: Issues, https://github.com/Imageomics/pybioclip/issues
Project-URL: Source, https://github.com/Imageomics/pybioclip
Author-email: John Bradley <johnbradley2008@gmail.com>
License-Expression: MIT
License-File: LICENSE
Classifier: Development Status :: 5 - Production/Stable
Classifier: Programming Language :: Python
Classifier: Programming Language :: Python :: 3.10
Classifier: Programming Language :: Python :: 3.11
Classifier: Programming Language :: Python :: 3.12
Classifier: Programming Language :: Python :: 3.13
Classifier: Programming Language :: Python :: Implementation :: CPython
Classifier: Programming Language :: Python :: Implementation :: PyPy
Requires-Python: >=3.10
Requires-Dist: open-clip-torch
Requires-Dist: pandas
Requires-Dist: prettytable
Requires-Dist: torch
Requires-Dist: torchvision
Provides-Extra: docs
Requires-Dist: mkdocs; extra == 'docs'
Requires-Dist: mkdocs-material; extra == 'docs'
Requires-Dist: mkdocs-material-extensions; extra == 'docs'
Requires-Dist: mkdocstrings-python; extra == 'docs'
